reflib/__init__.py
wg_reflib-0.1.0.dist-info/METADATA
wg_reflib-0.1.0.dist-info/RECORD
wg_reflib-0.1.0.dist-info/WHEEL
wg_reflib-0.1.0.dist-info/entry_points.txt
wg_reflib-0.1.0.dist-info/top_level.txt
