Metadata-Version: 2.1
Name: wg-reflib
Version: 0.1.0
Summary: Add references to the Wright group library
Home-page: http://wright.chem.wisc.edu
Author: Kyle Sunden
License: MIT
Platform: UNKNOWN
Classifier: Development Status :: 1 - Planning
Classifier: Environment :: Console
Classifier: Intended Audience :: Science/Research
Classifier: Programming Language :: Python :: 3
Classifier: License :: OSI Approved :: MIT License
Classifier: Topic :: Utilities
Requires-Python: >=3.6
Provides-Extra: dev
Requires-Dist: doi2bib
Requires-Dist: pybtex
Provides-Extra: dev
Requires-Dist: black; extra == 'dev'
Requires-Dist: pre-commit; extra == 'dev'
